ncdump_rich/__init__.py
ncdump_rich/__main__.py
ncdump_rich/ncdump.py
ncdump_rich-0.5.2.dist-info/METADATA
ncdump_rich-0.5.2.dist-info/WHEEL
ncdump_rich-0.5.2.dist-info/entry_points.txt
ncdump_rich-0.5.2.dist-info/licenses/LICENSE.rst
ncdump_rich-0.5.2.dist-info/RECORD
