Metadata-Version: 2.1
Name: ncdump-rich
Version: 0.5.2
Summary: Rich NcDump
Project-URL: changelog, https://github.com/engeir/ncdump-rich/releases
Project-URL: homepage, https://github.com/engeir/ncdump-rich
Project-URL: repository, https://github.com/engeir/ncdump-rich
Project-URL: documentation, https://ncdump-rich.readthedocs.io
Author-email: Eirik Enger <engeir@pm.me>
License-Expression: GPL-3.0
License-File: LICENSE.rst
Classifier: Development Status :: 5 - Production/Stable
Classifier: Programming Language :: Python :: 3.9
Classifier: Programming Language :: Python :: 3.10
Classifier: Programming Language :: Python :: 3.11
Classifier: Programming Language :: Python :: 3.12
Requires-Dist: click>=8.1.7
Requires-Dist: netcdf4>=1.6.5
Requires-Dist: rich-click>=1.7.3
Requires-Dist: rich>=13.7.0
